{
    "model": {
        "type": "minecraft:select",
        "property": "component",
        "component": "minecraft:custom_name",
        "fallback": {
            "type": "minecraft:model",
            "model": "minecraft:block/pink_glazed_terracotta"
        },
        "cases": [
            {
                "when": {
                    "color": "gold",
                    "text": "TARDIS Seed Block",
                    "italic": false
                },
                "model": {
                    "type": "minecraft:model",
                    "model": "tardis:item/seed/division"
                }
            },
            {
                "when": {
                    "color": "gold",
                    "text": "Division",
                    "italic": false
                },
                "model": {
                    "type": "minecraft:model",
                    "model": "tardis:item/seed/division"
                }
            },
            {
                "when": {
                    "text": "The Division Interuniverse Console"
                },
                "model": {
                    "type": "minecraft:model",
                    "model": "tardis:item/seed/division"
                }
            }
        ]
    }
}